fds/__init__.py
fds/sdk/__init__.py
fds/sdk/ProcuretoPayInvoiceandBilling/__init__.py
fds/sdk/ProcuretoPayInvoiceandBilling/api_client.py
fds/sdk/ProcuretoPayInvoiceandBilling/configuration.py
fds/sdk/ProcuretoPayInvoiceandBilling/exceptions.py
fds/sdk/ProcuretoPayInvoiceandBilling/model_utils.py
fds/sdk/ProcuretoPayInvoiceandBilling/rest.py
fds/sdk/ProcuretoPayInvoiceandBilling/api/__init__.py
fds/sdk/ProcuretoPayInvoiceandBilling/api/invoice_and_billing_api.py
fds/sdk/ProcuretoPayInvoiceandBilling/apis/__init__.py
fds/sdk/ProcuretoPayInvoiceandBilling/model/__init__.py
fds/sdk/ProcuretoPayInvoiceandBilling/model/account_detail.py
fds/sdk/ProcuretoPayInvoiceandBilling/model/accounts.py
fds/sdk/ProcuretoPayInvoiceandBilling/model/billing_address.py
fds/sdk/ProcuretoPayInvoiceandBilling/model/billing_adjustment.py
fds/sdk/ProcuretoPayInvoiceandBilling/model/error_object.py
fds/sdk/ProcuretoPayInvoiceandBilling/model/error_response.py
fds/sdk/ProcuretoPayInvoiceandBilling/model/invoice.py
fds/sdk/ProcuretoPayInvoiceandBilling/model/invoice_data.py
fds/sdk/ProcuretoPayInvoiceandBilling/model/product.py
fds/sdk/ProcuretoPayInvoiceandBilling/model/product_detail.py
fds/sdk/ProcuretoPayInvoiceandBilling/model/product_group.py
fds/sdk/ProcuretoPayInvoiceandBilling/model/product_groups.py
fds/sdk/ProcuretoPayInvoiceandBilling/model/service_detail.py
fds/sdk/ProcuretoPayInvoiceandBilling/model/statement_of_account.py
fds/sdk/ProcuretoPayInvoiceandBilling/model/subscription_change.py
fds/sdk/ProcuretoPayInvoiceandBilling/model/tax_detail.py
fds/sdk/ProcuretoPayInvoiceandBilling/models/__init__.py
fds_sdk_procuretopayinvoiceandbilling-0.2.0.dist-info/licenses/LICENSE
fds_sdk_procuretopayinvoiceandbilling-0.2.0.dist-info/METADATA
fds_sdk_procuretopayinvoiceandbilling-0.2.0.dist-info/WHEEL
fds_sdk_procuretopayinvoiceandbilling-0.2.0.dist-info/top_level.txt
fds_sdk_procuretopayinvoiceandbilling-0.2.0.dist-info/RECORD
